cykle/__init__.py
cykle/data/pre-push
cykle-0.2.10.dist-info/DESCRIPTION.rst
cykle-0.2.10.dist-info/METADATA
cykle-0.2.10.dist-info/RECORD
cykle-0.2.10.dist-info/WHEEL
cykle-0.2.10.dist-info/entry_points.txt
cykle-0.2.10.dist-info/metadata.json
cykle-0.2.10.dist-info/top_level.txt
