Metadata-Version: 2.0
Name: cykle
Version: 0.2.10
Summary: CLI for the happy coding process
Home-page: https://github.com/sangwonl/cykle
Author: Sangwon Lee
Author-email: gamzabaw@gmail.com
License: MIT
Keywords: development issue trello
Platform: UNKNOWN
Classifier: Development Status :: 3 - Alpha
Classifier: Intended Audience :: Developers
Classifier: Topic :: Software Development :: Bug Tracking
Classifier: License :: OSI Approved :: MIT License
Classifier: Programming Language :: Python :: 2
Classifier: Programming Language :: Python :: 2.6
Classifier: Programming Language :: Python :: 2.7
Requires-Dist: click (==6.2)
Requires-Dist: trello (==0.9.1)
Requires-Dist: PrettyTable (==0.7.2)
Requires-Dist: PyGithub (==1.26.0)
Requires-Dist: Fabric (==1.10.2)
Requires-Dist: configparser (==3.3.0r2)
Requires-Dist: requests (==2.9.1)
Requires-Dist: pycrypto (==2.6.1)
